MANIFEST.in
README.rst
setup.cfg
setup.py
pyretis/__init__.py
pyretis/version.py
pyretis/analysis/__init__.py
pyretis/analysis/analysis.py
pyretis/analysis/energy_analysis.py
pyretis/analysis/flux_analysis.py
pyretis/analysis/histogram.py
pyretis/analysis/order_analysis.py
pyretis/analysis/path_analysis.py
pyretis/core/__init__.py
pyretis/core/box.py
pyretis/core/common.py
pyretis/core/integrators.py
pyretis/core/montecarlo.py
pyretis/core/orderparameter.py
pyretis/core/particlefunctions.py
pyretis/core/particles.py
pyretis/core/path.py
pyretis/core/pathensemble.py
pyretis/core/properties.py
pyretis/core/random_gen.py
pyretis/core/retis.py
pyretis/core/system.py
pyretis/core/tis.py
pyretis/core/units.py
pyretis/core/simulation/__init__.py
pyretis/core/simulation/mc_simulation.py
pyretis/core/simulation/md_simulation.py
pyretis/core/simulation/path_simulation.py
pyretis/core/simulation/simulation.py
pyretis/core/simulation/simulation_task.py
pyretis/forcefield/__init__.py
pyretis/forcefield/factory.py
pyretis/forcefield/forcefield.py
pyretis/forcefield/potential.py
pyretis/forcefield/potentials/__init__.py
pyretis/forcefield/potentials/potentials.py
pyretis/forcefield/potentials/pairpotentials/__init__.py
pyretis/forcefield/potentials/pairpotentials/lennardjones.py
pyretis/forcefield/potentials/pairpotentials/pairpotential.py
pyretis/forcefield/potentials/pairpotentials/wca.py
pyretis/inout/__init__.py
pyretis/inout/common.py
pyretis/inout/analysisio/__init__.py
pyretis/inout/analysisio/analysisio.py
pyretis/inout/analysisio/analysistxt.py
pyretis/inout/plotting/__init__.py
pyretis/inout/plotting/mpl_plotting.py
pyretis/inout/plotting/plotting.py
pyretis/inout/plotting/styles/pyretis-old.mplstyle
pyretis/inout/plotting/styles/pyretis.mplstyle
pyretis/inout/report/__init__.py
pyretis/inout/report/markup.py
pyretis/inout/report/report.py
pyretis/inout/report/report_md.py
pyretis/inout/report/report_path.py
pyretis/inout/settings/__init__.py
pyretis_cecam_2016.egg-info/PKG-INFO
pyretis_cecam_2016.egg-info/SOURCES.txt
pyretis_cecam_2016.egg-info/dependency_links.txt
pyretis_cecam_2016.egg-info/requires.txt
pyretis_cecam_2016.egg-info/top_level.txt